gwtransforms/__init__.py
gwtransforms/autograd.py
gwtransforms/backend.py
gwtransforms/conversions.py
gwtransforms/utils.py
gwtransforms/compat/__init__.py
gwtransforms/compat/dataarray.py
gwtransforms/compat/dataframe.py
gwtransforms/transforms/__init__.py
gwtransforms/transforms/base.py
gwtransforms/transforms/distance.py
gwtransforms/transforms/mass.py
gwtransforms/transforms/symbolic.py
gwtransforms-0.2.0.dist-info/METADATA
gwtransforms-0.2.0.dist-info/WHEEL
gwtransforms-0.2.0.dist-info/licenses/LICENSE
gwtransforms-0.2.0.dist-info/RECORD
