Metadata-Version: 2.4
Name: gwtransforms
Version: 0.2.0
Summary: Coordinate and parameter transformations for gravitational-wave related calculations.
Project-URL: Homepage, https://github.com/binado/gwtransforms
Author-email: Bernardo Veronese <bernardopveronese@gmail.com>
License-File: LICENSE
Requires-Python: >=3.11
Requires-Dist: astropy[recommended]>=7.1.0
Requires-Dist: numpy>=2.3.1
Provides-Extra: dataarray
Requires-Dist: xarray>=2025.6.1; extra == 'dataarray'
Provides-Extra: dataframe
Requires-Dist: pandas-stubs>=2.2.3.250527; extra == 'dataframe'
Requires-Dist: pandas>=2.3.0; extra == 'dataframe'
Provides-Extra: symbolic
Requires-Dist: sympy>=1.14.0; extra == 'symbolic'
